{
  "project_info": {
    "project_number": "610443387774",
    "project_id": "dokandar-316216",
    "storage_bucket": "dokandar-316216.appspot.com"
  },
  "client": [
    {
      "client_info": {
        "mobilesdk_app_id": "1:610443387774:android:f131427bd533712b60892f",
        "android_client_info": {
          "package_name": "delivery.dokandar.xyz"
        }
      },
      "oauth_client": [
        {
          "client_id": "610443387774-4k5qqcel0sntd7q3ap23rk1gvj9hj4oe.apps.googleusercontent.com",
          "client_type": 3
        }
      ],
      "api_key": [
        {
          "current_key": "AIzaSyDNtJMAKKfqKgW8cjshI9n6AWE9CKQA5KE"
        }
      ],
      "services": {
        "appinvite_service": {
          "other_platform_oauth_client": [
            {
              "client_id": "610443387774-4k5qqcel0sntd7q3ap23rk1gvj9hj4oe.apps.googleusercontent.com",
              "client_type": 3
            }
          ]
        }
      }
    },
    {
      "client_info": {
        "mobilesdk_app_id": "1:610443387774:android:7cc689678118c5d560892f",
        "android_client_info": {
          "package_name": "store.dokandar.xyz"
        }
      },
      "oauth_client": [
        {
          "client_id": "610443387774-4k5qqcel0sntd7q3ap23rk1gvj9hj4oe.apps.googleusercontent.com",
          "client_type": 3
        }
      ],
      "api_key": [
        {
          "current_key": "AIzaSyDNtJMAKKfqKgW8cjshI9n6AWE9CKQA5KE"
        }
      ],
      "services": {
        "appinvite_service": {
          "other_platform_oauth_client": [
            {
              "client_id": "610443387774-4k5qqcel0sntd7q3ap23rk1gvj9hj4oe.apps.googleusercontent.com",
              "client_type": 3
            }
          ]
        }
      }
    }
  ],
  "configuration_version": "1"
}